oxcgrt/__init__.py
oxcgrt-0.0.1.dist-info/LICENSE
oxcgrt-0.0.1.dist-info/WHEEL
oxcgrt-0.0.1.dist-info/METADATA
oxcgrt-0.0.1.dist-info/RECORD
